Workbook

Sheet Hoja1
A1: Tipo de activación y abono | B1: Precio
A2: Antena NOVATEL L1-L2 Señal libre de 15 cm | B2: {='lista de precios 824'!F4:F7} -> 16575
A3: Antena NOVATEL L1-L2 ACTIVACIÓN SIN abono 15 CM | B3: 17990.7
A4: Antena NOVATEL L1-L2 ACTIVACIÓN y ABONO TRIMESTRAL 2,5 CM | B4: 18946.6
A5: Antena NOVATEL L1-L2 ACTIVACIÓN y ABONO ANUAL 2,5 CM | B5: 19660.5
A6: SURVEY L1 CON base portátil RTK | B6: ='lista de precios 824'!F18 -> 16575
A7: SURVEY L1 SIN base portátil RTK | B7: ='lista de precios 824'!F19 -> 13812.5
A8: Abono ANUAL: con corr. TERRASTAR C PRO de 2,5 cm. | B8: ='lista de precios 824'!F12 -> 1669.8
A9: Abono TRIMESTRAL: con corr. TERRASTAR C PRO de 2,5 cm. | B9: ='lista de precios 824'!F13 -> 955.9
A10: ACTIVACION de la ANTENA NOVATEL para TERRASTAR C PRO (única vez) | B10: ='lista de precios 824'!F14 -> 1415.7

Sheet lista de precios 824
B1: Lista 0225 | C1: PILOTOS ControlAgro INTEGRA 6000 c/Giro en Cabecera
B2: PILOTO AUTOMATICO CON ANTENA NOVATEL PARA ABONO DE PRECISION
B3: DETALLE DE LA ACTIVACION Y ABONOS | E3: NETO | F3: CON IVA 10,5%
B4: Equipo piloto automático INTEGRA 6000, pantalla 10 pulg. táctil, con Giro en Cabecera, volante con motor eléctrico y antena NOVATEL L1-L2 con señal libre de 15 cm | E4: 15000 | F4: =+E4*1.105 -> 16575
B5: Equipo piloto automático INTEGRA 6000, pantalla 10 pulg. táctil, con Giro en Cabecera, volante con motor eléctrico y antena NOVATEL L1-L2 con ACTIVACION, SIN abono, con 15 CM de PRECISION | E5: ='lista de precios 824'!E4+E14 -> 16170 | F5: =('lista de precios 824'!E4 * 1.105)+F14 -> 17990.7
B6: Equipo piloto automático INTEGRA 6000, pantalla 10 pulg. táctil, con Giro en Cabecera, volante con motor eléctrico y Antena NOVATEL L1-L2 con ACTIVACION y ABONO TRIMESTRAL con 2,5 CM de PRECISION | E6: ='lista de precios 824'!E4+E14+E13 -> 16960 | F6: =('lista de precios 824'!E4 * 1.105)+F13+F14 -> 18946.6
B7: Equipo piloto automático INTEGRA 6000, pantalla 10 pulg. táctil, con Giro en Cabecera, volante con motor eléctrico y antena NOVATEL L1-L2 con ACTIVACION y ABONO ANUAL con 2,5 CM de PRECISION | E7: ='lista de precios 824'!E4+E14+E12 -> 17550 | F7: =('lista de precios 824'!E4 * 1.105)+F14+F12 -> 19660.5
B8: DOLAR DE REFERENCIA: DÓLAR BILLETE BANCO NACION TIPO VENDEDOR
B9: *OBSERVACIONES: LAS ACTIVACIONES Y ABONOS NO TIENEN COMISIONES.
B10: COSTO DE SEÑAL TERRESTAR C
B11: DETALLE DE LA ACTIVACION Y ABONOS | E11: NETO | F11: CON IVA 21% - CONTADO
B12: Abono ANUAL: con corr. TERRASTAR C PRO de 2,5 cm. por 1 año | E12: 1380 | F12: =E12*1.21 -> 1669.8
B13: Abono TRIMESTRAL: con corr. TERRASTAR C PRO de 2,5 cm. por 3 meses | E13: 790 | F13: =E13*1.21 -> 955.9
B14: ACTIVACION de la ANTENA NOVATEL para TERRASTAR C PRO (unica vez) | E14: 1170 | F14: =E14*1.21 -> 1415.7
B15: DOLAR DE REFERENCIA: DÓLAR BILLETE BANCO NACION TIPO VENDEDOR
B16: PILOTO AUTOMATICO CON BASE PORTATIL PARA ANTENA RTK
B17: DETALLE DEL EQUIPO | E17: PRECIO DE LISTA NETO | F17: PRECIO DE LISTA CON IVA 10,5%
B18: Equipo piloto automático INTEGRA 6000, pantalla 10 pulg. táctil, con giro en cabecera, volante con motor eléctrico, y antena con base portatil RTK, con precisión de 2,5 cm | E18: 15000 | F18: =+E18*1.105 -> 16575
B19: Equipo piloto automático INTEGRA 6000, pantalla 10 pulg., con Giro en Cabecera, Antena SURVEY L1 (compatible pero sin base RTK, SIN abonos), volante con motor eléc., con señal libre con precisión de 15 cm | E19: 12500 | F19: =+E19*1.105 -> 13812.5
B20: DOLAR DE REFERENCIA: DÓLAR BILLETE BANCO NACION TIPO VENDEDOR
B22: DETALLE del BANDERILLERO INTEGRA 6000 | E22: NETO | F22: CON IVA 10,5%
B23: Equipo banderillero con pantalla 10 pulg. táctil mapeador con antena de 10 hertz, apto para agregar futuro Piloto automático con Antena RTK o con Ant. Novatel con Abono, Cortes por Surco o monitor de siembra con dosis variable. | E23: 3300 | F23: =+E23*1.105 -> 3646.5
B25: KIT ADICIONAL CABLES PILOTO INTEGRA 6000 | E25: NETO | F25: CON IVA 10,5%
B26: KIT PARA PODER TRASLADAR EL PILOTO A UN SEGUNDO TRACTOR, COSECHADORA O PULVERIZADORA. | E26: 2500 | F26: =+E26*1.21 -> 3025
B29: FORMAS DE PAGO : para Pilotos y Banderilleros
B30: * CONTADO: 10% DESCUENTO SOBRE PRECIO DE LISTA
B31: * FINANCIACIÓN 120, EN PESOS, 5 CHEQUES a 0, 30 60 90 Y 120 EN PESOS SIN INTERES.
B34: FINANCIACIÓN EN DOLARES AJUSTABLE: excepto Banderilleros
B35: *FINANCIACIÓN con ANTICIPO 25%, y SALDO EN 11 CHEQUES AJUSTABLES, QUE SERIAN DESDE 30, 60,..hasta..., 330, 360 DIAS.
B36: *Mediante CANJE CEREAL con AGROCANJE PILOTO con RTK: ANTICIPO DEL 30 % EN $$, Y 2 ENTREGAS DE CEREAL A 6 Y 12 MESES.

Sheet COTIZ. ANTENA NOVATEL
B1: =+'lista de precios 824'!B1 -> Lista 0225 | C1: PILOTOS AUTOMATICOS INTEGRA 6000 con Giro en Cabecera
B2: PILOTO AUTOMATICO CON ANTENA NOVATEL pars ABONO DE PRECISION
B3: COTIZACION DEL EQUIPO | E3: PRECIO DE LISTA NETO | F3: PRECIO DE LISTA CON IVA 10,5%
B4: Equipo piloto automático INTEGRA 6000, pantalla 10 pulg. táctil, con giro en cabecera, volante con motor eléctrico y antena NOVATEL L1-L2 con SEÑAL LIBRE de 15 cm de PRECISION. | E4: ='lista de precios 824'!E4 -> 15000 | F4: =+E4*1.105 -> 16575
B5: Equipo piloto automático INTEGRA 6000, pantalla 10 pulg. táctil, con giro en cabecera, volante con motor eléctrico y antena NOVATEL L1-L2 con ACTIVACION TERRASTAR SIN abono, con 15 CM de PRECISION | E5: ='lista de precios 824'!E4+E16 -> 16170 | F5: =('lista de precios 824'!E4 * 1.105)+F16 -> 17990.7
B6: Equipo piloto automático INTEGRA 6000, pantalla 10 pulg. táctil, con giro en cabecera, volante con motor eléctrico y Antena NOVATEL L1-L2 con ACTIVACION y señal con ABONO TRIMESTRAL con 2,5 CM de PRECISION | E6: ='lista de precios 824'!E4+E16+E14 -> 16960 | F6: =('lista de precios 824'!E4 * 1.105)+F16+F14 -> 18946.6
B7: Equipo piloto automático INTEGRA 6000, pantalla 10 pulg. táctil, con giro en cabecera, volante con motor eléctrico y antena NOVATEL L1-L2 con ACTIVACION y señal con ABONO ANUAL con 2,5 CM de PRECISION | E7: ='lista de precios 824'!E4+E16+E13 -> 17550 | F7: =('lista de precios 824'!E4 * 1.105)+F16+F13 -> 19660.5
B8: DOLAR DE REFERENCIA: DÓLAR BILLETE BANCO NACION TIPO VENDEDOR
B10: COSTO DE SEÑAL TERRESTAR C PRO
B12: DETALLE DE LA ACTIVACION Y ABONOS | E12: NETO | F12: CON IVA 21% - CONTADO
B13: ABONO de la Señal con corrección TERRASTAR C PRO de 2,5 cm. por 1 año (pagos anuales) | E13: =+'lista de precios 824'!E12 -> 1380 | F13: =E13*1.21 -> 1669.8
B14: ABONO de la Señal con corrección TERRASTAR C PRO de 2,5 cm. por 3 MESES (pagos trimestrales) | E14: =+'lista de precios 824'!E13 -> 790 | F14: =E14*1.21 -> 955.9
B16: Con ACTIVACION de la Antena para TERRASTAR C PRO , le transfiere un precision de 15 cm (pago por unica vez SIEMPRE) | E16: =+'lista de precios 824'!E14 -> 1170 | F16: =E16*1.21 -> 1415.7
B18: FORMA DE PAGO DE LA ACTIVACION Y LOS ABONOS: ANTICIPADO
B20: FORMAS DE PAGO en $: para Pilotos y Banderilleros
B21: * CONTADO: 10% DESCUENTO SOBRE PRECIO DE LISTA
B22: * FINANCIACIÓN A 120 DÍAS EN PESOS, SIN INTERES, 5 CHEQUES DE 0, 30 60 90 Y 120 EN PESOS SIN INTERES.
B25: FINANCIACIÓN EN DOLARES AJUSTABLE:
B26: *FINANCIACIÓN con ANTICIPO 25%, y SALDO EN 12 CHEQUES AJUSTABLES, QUE SERIAN DESDE 30, 60,…hasta..., 330, 360 DIAS.
B27: *Mediante CANJE CEREAL con AGROCANJE: ANTICIPO DEL 30% EN $$, Y 2 ENTREGAS DE CEREAL A 6 Y 12 MESES MAXIMO.

Sheet COTIZ. ANTENA RTK
B1: =+'lista de precios 824'!B1 -> Lista 0225 | C1: PILOTOS AUTOMATICOS INTEGRA 6000 con Giro en Cabecera
B2: PILOTO AUTOMATICO CON BASE PORTATIL PARA ANTENA RTK
B3: COTIZACION DEL EQUIPO | E3: PRECIO DE LISTA NETO | F3: PRECIO DE LISTA CON IVA 10,5%
B4: Equipo piloto automático INTEGRA 6000, pantalla 10 pulg. táctil, con Giro en Cabecera, Antena SURVEY L1, volante con motor eléctrico, y Antena con base portatil RTK, con precisión de 2,5 cm | E4: =+'lista de precios 824'!E18 -> 15000 | F4: =+E4*1.105 -> 16575
B5: Equipo piloto automático INTEGRA 6000, pantalla 10 pulg., con Giro en Cabec., Antena SURVEY L1 (compatible pero SIN base RTK, no apto para abonos), volante con motor eléc., con señal libre con precisión de 15 cm | E5: =+'lista de precios 824'!E19 -> 12500 | F5: =+E5*1.105 -> 13812.5
B6: DOLAR DE REFERENCIA: DÓLAR BILLETE BANCO NACION TIPO VENDEDOR
B8: FORMAS DE PAGO en $: para Pilotos y Banderilleros
B9: * CONTADO: 10% DESCUENTO SOBRE PRECIO DE LISTA
B10: * FINANCIACIÓN A 120 DÍAS EN PESOS, SIN INTERES, 5 CHEQUES DE 0, 30 60 90 Y 120 EN PESOS SIN INTERES.
B13: FINANCIACIÓN EN DOLARES AJUSTABLE:
B14: *FINANCIACIÓN con ANTICIPO 25%, y SALDO EN 12 CHEQUES AJUSTABLES, QUE SERIAN DESDE 30, 60,..., 330, 360 DIAS.
B15: *Mediante CANJE CEREAL con AGROCANJE: ANTICIPO DEL 30% EN $$, Y 2 ENTREGAS DE CEREAL A 6 Y 12 MESES MAXIMO.
